[
  {
    "user": {
      "screenName": "ektrit",
      "name": "WAR ECONOMY by KRIS 📿",
      "followersCount": 12341
    },
    "images": [
      "https://pbs.twimg.com/media/G_5VqhOXsAALuSL.jpg"
    ],
    "videos": [],
    "tweetUrl": "https://x.com/ektrit/status/2017144034209222701",
    "fullText": "JAN 30 2026 WAR ECONOMY NEWSLETTER\n\nhttps://t.co/1Csxlsxqoe\n\n https://t.co/gHy2SGTYyo https://t.co/AOoLguwkCG",
    "createdAt": "Fri Jan 30 07:53:09 +0000 2026",
    "metrics": {
      "likes": 0,
      "retweets": 0,
      "replies": 0,
      "views": "102"
    }
  },
  {
    "user": {
      "screenName": "NobelPrize",
      "name": "The Nobel Prize",
      "followersCount": 1309947
    },
    "images": [
      "https://pbs.twimg.com/media/G_41ghHWAAEEYyl.jpg",
      "https://pbs.twimg.com/media/G_41hu6XgAAXXsW.jpg"
    ],
    "videos": [],
    "tweetUrl": "https://x.com/NobelPrize/status/2017108558047838281",
    "fullText": "Highlighting the co-inventor of the LED, Isamu Akasaki (赤崎 勇).\n\nIlluminating our world by inventing a new energy-efficient and environment-friendly light source – the blue light-emitting diode LED – Akasaki was awarded the 2014 #NobelPrize in Physics. https://t.co/N8fIyOlUZB",
    "createdAt": "Fri Jan 30 05:32:10 +0000 2026",
    "metrics": {
      "likes": 0,
      "retweets": 0,
      "replies": 0,
      "views": "4342"
    }
  },
  {
    "user": {
      "screenName": "stlouisfed",
      "name": "St. Louis Fed",
      "followersCount": 244065
    },
    "images": [],
    "videos": [
      "https://video.twimg.com/ext_tw_video/2017094927147057152/pu/vid/avc1/480x270/PgdX7G5Sf56bp2li.mp4?tag=12"
    ],
    "tweetUrl": "https://x.com/stlouisfed/status/2017094969299747235",
    "fullText": "The St. Louis Fed is part of the Federal Reserve System and serves the Eighth Federal Reserve District. Our District helps define us: https://t.co/RuQBFfk0yT https:// https://t.co/vQ46rkNtKe",
    "createdAt": "Fri Jan 30 04:38:11 +0000 2026",
    "metrics": {
      "likes": 0,
      "retweets": 0,
      "replies": 0,
      "views": "1368"
    }
  },
  {
    "user": {
      "screenName": "elerianm",
      "name": "Mohamed A. El-Erian",
      "followersCount": 803876
    },
    "images": [
      "https://pbs.twimg.com/media/G_4eUbpW8AAhxXf.png",
      "https://pbs.twimg.com/media/G_4eXO7WQAAbxUF.jpg"
    ],
    "videos": [],
    "tweetUrl": "https://x.com/elerianm/status/2017083282760818975",
    "fullText": "With President Trump set to announce his pick for Fed Chair in just a few hours, the odds in the \"prediction markets\" -- as shown below by Polymarket -- have shifted firmly in favor of Kevin Warsh.\n#economy #markets #federalreserve #FedChair https://t.co/YC4PwpQIy2",
    "createdAt": "Fri Jan 30 03:51:44 +0000 2026",
    "metrics": {
      "likes": 0,
      "retweets": 0,
      "replies": 0,
      "views": "25059"
    }
  },
  {
    "user": {
      "screenName": "WSJmarkets",
      "name": "WSJ Markets",
      "followersCount": 1021083
    },
    "images": [],
    "videos": [],
    "tweetUrl": "https://x.com/WSJmarkets/status/2017078469813788843",
    "fullText": "London Metal Exchange Resumes Trade After Technical Glitch https://t.co/dGYQf0jpMM",
    "createdAt": "Fri Jan 30 03:32:37 +0000 2026",
    "metrics": {
      "likes": 0,
      "retweets": 0,
      "replies": 0,
      "views": "3542"
    }
  },
  {
    "user": {
      "screenName": "stlouisfed",
      "name": "St. Louis Fed",
      "followersCount": 244065
    },
    "images": [
      "https://pbs.twimg.com/media/G_4V7DDWUAA7tK4.jpg"
    ],
    "videos": [],
    "tweetUrl": "https://x.com/stlouisfed/status/2017073808046264683",
    "fullText": ".@uscensusbureau estimates the number of people living in poverty in the U.S. In 2023, that number was 40,763,043 people. Visit the FRED Blog to learn more about the math and the methods https://t.co/L4pnUvqeHD https://t.co/RnzL8XLgBK",
    "createdAt": "Fri Jan 30 03:14:05 +0000 2026",
    "metrics": {
      "likes": 0,
      "retweets": 0,
      "replies": 0,
      "views": "1712"
    }
  },
  {
    "user": {
      "screenName": "WSJmarkets",
      "name": "WSJ Markets",
      "followersCount": 1021083
    },
    "images": [],
    "videos": [],
    "tweetUrl": "https://x.com/WSJmarkets/status/2017070905243869505",
    "fullText": "Prices for gold, silver and platinum have surged to record levels, and individual investors are celebrating. The pros? Not so much. https://t.co/BfciMgP71b",
    "createdAt": "Fri Jan 30 03:02:33 +0000 2026",
    "metrics": {
      "likes": 0,
      "retweets": 0,
      "replies": 0,
      "views": "3541"
    }
  },
  {
    "user": {
      "screenName": "NickTimiraos",
      "name": "Nick Timiraos",
      "followersCount": 458612
    },
    "images": [],
    "videos": [],
    "tweetUrl": "https://x.com/NickTimiraos/status/2017058872582676686",
    "fullText": "Fed chair contender Kevin Warsh met with President Trump at the White House on Thursday. \n\nTrump told reporters that he planned to unveil his Fed chair pick on Friday.\n\nTrump said he didn't want to reveal his pick but said of his choice: “A lot of people think that this is",
    "createdAt": "Fri Jan 30 02:14:45 +0000 2026",
    "metrics": {
      "likes": 0,
      "retweets": 0,
      "replies": 0,
      "views": "190866"
    }
  },
  {
    "user": {
      "screenName": "WSJmarkets",
      "name": "WSJ Markets",
      "followersCount": 1021083
    },
    "images": [],
    "videos": [],
    "tweetUrl": "https://x.com/WSJmarkets/status/2017055257524633774",
    "fullText": "Coinbase chief Brian Armstrong is clashing with Jamie Dimon and other bank stewards over the future of finance https://t.co/P8Wt6B8h1E",
    "createdAt": "Fri Jan 30 02:00:23 +0000 2026",
    "metrics": {
      "likes": 0,
      "retweets": 0,
      "replies": 0,
      "views": "3301"
    }
  },
  {
    "user": {
      "screenName": "stlouisfed",
      "name": "St. Louis Fed",
      "followersCount": 244065
    },
    "images": [
      "https://pbs.twimg.com/media/G_4FBKRWkAATx-U.png"
    ],
    "videos": [],
    "tweetUrl": "https://x.com/stlouisfed/status/2017055221399122228",
    "fullText": "The trimmed mean PCE inflation rate decreased to 2.49% for the 12 months ending in November, down from 2.54% in October. For more on the @DallasFed alternative measure of core inflation, see FRED: https://t.co/38EdwMwAJ7 https://t.co/tff3CVBCsv",
    "createdAt": "Fri Jan 30 02:00:14 +0000 2026",
    "metrics": {
      "likes": 0,
      "retweets": 0,
      "replies": 0,
      "views": "1571"
    }
  },
  {
    "user": {
      "screenName": "stlouisfed",
      "name": "St. Louis Fed",
      "followersCount": 244065
    },
    "images": [
      "https://pbs.twimg.com/media/G_4BjeEWEAAy7lW.jpg"
    ],
    "videos": [],
    "tweetUrl": "https://x.com/stlouisfed/status/2017051412719431901",
    "fullText": "In the week ending Jan. 29, average fixed mortgage rates rose, to 6.10% for the 30-year and 5.49% for the 15-year https://t.co/Dg5tLZxdqf https://t.co/pGWNo28qjQ",
    "createdAt": "Fri Jan 30 01:45:06 +0000 2026",
    "metrics": {
      "likes": 0,
      "retweets": 0,
      "replies": 0,
      "views": "3190"
    }
  },
  {
    "user": {
      "screenName": "cnnbrk",
      "name": "CNN Breaking News",
      "followersCount": 59265651
    },
    "images": [],
    "videos": [],
    "tweetUrl": "https://x.com/cnnbrk/status/2017049263654449468",
    "fullText": "President Trump sues the IRS and Treasury Department for at least $10 billion, alleging an unauthorized leak of his tax returns in his first term. \nhttps://t.co/Emw9YtJBKh",
    "createdAt": "Fri Jan 30 01:36:34 +0000 2026",
    "metrics": {
      "likes": 0,
      "retweets": 0,
      "replies": 0,
      "views": "145868"
    }
  },
  {
    "user": {
      "screenName": "WSJmarkets",
      "name": "WSJ Markets",
      "followersCount": 1021083
    },
    "images": [],
    "videos": [],
    "tweetUrl": "https://x.com/WSJmarkets/status/2017045829744198086",
    "fullText": "Oil Prices Mixed; Lingering U.S.-Iran Tensions May Support https://t.co/bOX69sOA2f",
    "createdAt": "Fri Jan 30 01:22:55 +0000 2026",
    "metrics": {
      "likes": 0,
      "retweets": 0,
      "replies": 0,
      "views": "3312"
    }
  },
  {
    "user": {
      "screenName": "CookPolitical",
      "name": "Cook Political Report",
      "followersCount": 213885
    },
    "images": [],
    "videos": [],
    "tweetUrl": "https://x.com/CookPolitical/status/2017041973316600126",
    "fullText": "The contest to be California’s next governor is finally coming into focus — even if the Democratic field still remains murky.\n\nRead more from @JessicaTaylor:\n\nhttps://t.co/CsFbJSHumQ",
    "createdAt": "Fri Jan 30 01:07:35 +0000 2026",
    "metrics": {
      "likes": 0,
      "retweets": 0,
      "replies": 0,
      "views": "4471"
    }
  },
  {
    "user": {
      "screenName": "PaulPortesi",
      "name": "Paul Portesi",
      "followersCount": 10685
    },
    "images": [],
    "videos": [],
    "tweetUrl": "https://x.com/PaulPortesi/status/2017038686588965165",
    "fullText": "You took the easy way out; now it's going to be the hard way. \n\nTime just hasn't shown it to you yet.\n\nHard early, easy later.\n\nEasy now, is going to be hard.",
    "createdAt": "Fri Jan 30 00:54:32 +0000 2026",
    "metrics": {
      "likes": 0,
      "retweets": 0,
      "replies": 0,
      "views": "1195"
    }
  },
  {
    "user": {
      "screenName": "stlouisfed",
      "name": "St. Louis Fed",
      "followersCount": 244065
    },
    "images": [
      "https://pbs.twimg.com/media/G_3xiGrXUAA3xie.jpg"
    ],
    "videos": [],
    "tweetUrl": "https://x.com/stlouisfed/status/2017033796701323269",
    "fullText": "In the week ending Jan. 24, seasonally adjusted initial claims for unemployment insurance benefits—those filed for the first time after a job loss—decreased by 1,000, to 209,000. The four-week moving average rose to 206,250 https://t.co/ukmfsI5cdS https://t.co/AwEFtK2LbP",
    "createdAt": "Fri Jan 30 00:35:06 +0000 2026",
    "metrics": {
      "likes": 0,
      "retweets": 0,
      "replies": 0,
      "views": "1624"
    }
  },
  {
    "user": {
      "screenName": "NickTimiraos",
      "name": "Nick Timiraos",
      "followersCount": 458612
    },
    "images": [],
    "videos": [],
    "tweetUrl": "https://x.com/NickTimiraos/status/2017033777671778606",
    "fullText": "Trump told reporters he'd announce his pick for the Fed on Friday morning https://t.co/wgMf3AWhIX",
    "createdAt": "Fri Jan 30 00:35:01 +0000 2026",
    "metrics": {
      "likes": 0,
      "retweets": 0,
      "replies": 0,
      "views": "38267"
    }
  },
  {
    "user": {
      "screenName": "WSJmarkets",
      "name": "WSJ Markets",
      "followersCount": 1021083
    },
    "images": [],
    "videos": [],
    "tweetUrl": "https://x.com/WSJmarkets/status/2017033492496818619",
    "fullText": "Asian Currencies Consolidate; Ongoing U. S-Iran Tensions May Weigh https://t.co/5FJeMdaxCF",
    "createdAt": "Fri Jan 30 00:33:53 +0000 2026",
    "metrics": {
      "likes": 0,
      "retweets": 0,
      "replies": 0,
      "views": "7336"
    }
  },
  {
    "user": {
      "screenName": "WSJmarkets",
      "name": "WSJ Markets",
      "followersCount": 1021083
    },
    "images": [],
    "videos": [],
    "tweetUrl": "https://x.com/WSJmarkets/status/2017029258019815795",
    "fullText": "JGB Futures Edge Higher, Tracking Price Gains in U.S. Treasury Market https://t.co/gId4Brb30t",
    "createdAt": "Fri Jan 30 00:17:04 +0000 2026",
    "metrics": {
      "likes": 0,
      "retweets": 0,
      "replies": 0,
      "views": "2809"
    }
  },
  {
    "user": {
      "screenName": "mikeharrisNY",
      "name": "Michael Harris ∀p(p→◊Kp)",
      "followersCount": 32777
    },
    "images": [],
    "videos": [],
    "tweetUrl": "https://x.com/mikeharrisNY/status/2017025540230652347",
    "fullText": "That dumped #silver paper but spot arbitragers, probably the big commodity firms, came in and the markets rebounded hard, eyeing new highs now.",
    "createdAt": "Fri Jan 30 00:02:17 +0000 2026",
    "metrics": {
      "likes": 0,
      "retweets": 0,
      "replies": 0,
      "views": "772"
    }
  },
  {
    "user": {
      "screenName": "WSJmarkets",
      "name": "WSJ Markets",
      "followersCount": 1021083
    },
    "images": [],
    "videos": [],
    "tweetUrl": "https://x.com/WSJmarkets/status/2017025294805147700",
    "fullText": "Gold Rises Amid Ongoing Iran Tensions https://t.co/CvWY4y9jpD",
    "createdAt": "Fri Jan 30 00:01:19 +0000 2026",
    "metrics": {
      "likes": 0,
      "retweets": 0,
      "replies": 0,
      "views": "2915"
    }
  },
  {
    "user": {
      "screenName": "mikeharrisNY",
      "name": "Michael Harris ∀p(p→◊Kp)",
      "followersCount": 32777
    },
    "images": [],
    "videos": [],
    "tweetUrl": "https://x.com/mikeharrisNY/status/2017022076360536241",
    "fullText": "If we lower rates to zero, the Chinese will surrender, the Russians will dissolve to 10 countries, the Iranians will get Monarchy, Greenland will beg to get annexed, Venezuela will get Puerto Rico status, 1 BTC will worth 10 BTC, and AI will make our breakfast and dinner.",
    "createdAt": "Thu Jan 29 23:48:32 +0000 2026",
    "metrics": {
      "likes": 0,
      "retweets": 0,
      "replies": 0,
      "views": "1361"
    }
  },
  {
    "user": {
      "screenName": "stlouisfed",
      "name": "St. Louis Fed",
      "followersCount": 244065
    },
    "images": [
      "https://pbs.twimg.com/media/G_3k8p2WAAATmv8.jpg"
    ],
    "videos": [],
    "tweetUrl": "https://x.com/stlouisfed/status/2017019959541449113",
    "fullText": "The FRED Blog checks the math to better understand how the @uscensusbureau measures the poverty level in the U.S. https://t.co/ollPhvM505 https://t.co/DmComRAzFt",
    "createdAt": "Thu Jan 29 23:40:07 +0000 2026",
    "metrics": {
      "likes": 0,
      "retweets": 0,
      "replies": 0,
      "views": "1682"
    }
  },
  {
    "user": {
      "screenName": "cnnbrk",
      "name": "CNN Breaking News",
      "followersCount": 59265651
    },
    "images": [
      "https://pbs.twimg.com/media/G_3ht0NXIAAEEGI.jpg"
    ],
    "videos": [],
    "tweetUrl": "https://x.com/cnnbrk/status/2017016406282313892",
    "fullText": "Senate Democratic Leader Chuck Schumer's office says a bipartisan funding deal has been reached to avert a government shutdown. GOP Senate leaders are now working to schedule a vote. https://t.co/VQQSDikQWd https://t.co/Rqx91nR2Fc",
    "createdAt": "Thu Jan 29 23:26:00 +0000 2026",
    "metrics": {
      "likes": 0,
      "retweets": 0,
      "replies": 0,
      "views": "148072"
    }
  },
  {
    "user": {
      "screenName": "PolitiFact",
      "name": "PolitiFact",
      "followersCount": 584950
    },
    "images": [],
    "videos": [],
    "tweetUrl": "https://x.com/PolitiFact/status/2017012871301824922",
    "fullText": "About two months after the last federal government shutdown ended, another funding lapse looms. Democrats are balking at funding immigration enforcement without policy changes. How could it play out?\n\nhttps://t.co/mblacKoWp2",
    "createdAt": "Thu Jan 29 23:11:57 +0000 2026",
    "metrics": {
      "likes": 0,
      "retweets": 0,
      "replies": 0,
      "views": "4463"
    }
  },
  {
    "user": {
      "screenName": "WSJmarkets",
      "name": "WSJ Markets",
      "followersCount": 1021083
    },
    "images": [],
    "videos": [],
    "tweetUrl": "https://x.com/WSJmarkets/status/2017000522448769250",
    "fullText": "Disappointing earnings from Microsoft fueled a wider tech selloff Thursday https://t.co/JusKQHZQrD",
    "createdAt": "Thu Jan 29 22:22:53 +0000 2026",
    "metrics": {
      "likes": 0,
      "retweets": 0,
      "replies": 0,
      "views": "3432"
    }
  },
  {
    "user": {
      "screenName": "Porkchop_EXP",
      "name": "Porkchop Express",
      "followersCount": 15811
    },
    "images": [],
    "videos": [],
    "tweetUrl": "https://x.com/Porkchop_EXP/status/2016991265884123413",
    "fullText": "A woman is now safer in Dubai than in a large Western European city. Let that sink in.",
    "createdAt": "Thu Jan 29 21:46:06 +0000 2026",
    "metrics": {
      "likes": 0,
      "retweets": 0,
      "replies": 0,
      "views": "1607"
    }
  },
  {
    "user": {
      "screenName": "mikeharrisNY",
      "name": "Michael Harris ∀p(p→◊Kp)",
      "followersCount": 32777
    },
    "images": [],
    "videos": [],
    "tweetUrl": "https://x.com/mikeharrisNY/status/2016986235902824642",
    "fullText": "If you shorted #silver or #gold intraday due to the reversal, there is a word for such actions. 😂Our strategies are out of paper gold due to a special rule, but I am long physical, and although I will not add now, I will never sell even a small fraction.",
    "createdAt": "Thu Jan 29 21:26:07 +0000 2026",
    "metrics": {
      "likes": 0,
      "retweets": 0,
      "replies": 0,
      "views": "844"
    }
  },
  {
    "user": {
      "screenName": "lavitalenta",
      "name": "lavitalenta",
      "followersCount": 46130
    },
    "images": [
      "https://pbs.twimg.com/media/G_3E1CwbcAAeFme.jpg"
    ],
    "videos": [],
    "tweetUrl": "https://x.com/lavitalenta/status/2016984657607479690",
    "fullText": "Johann Wolfgang von Goethe was right to exclaim in 1786 that — “the whole history of the world attaches itself to this spot.” https://t.co/G9zZNOMtJh",
    "createdAt": "Thu Jan 29 21:19:50 +0000 2026",
    "metrics": {
      "likes": 0,
      "retweets": 0,
      "replies": 0,
      "views": "1069"
    }
  },
  {
    "user": {
      "screenName": "cnnbrk",
      "name": "CNN Breaking News",
      "followersCount": 59265651
    },
    "images": [],
    "videos": [],
    "tweetUrl": "https://x.com/cnnbrk/status/2016978247569830047",
    "fullText": "A Minnesota man was arrested on charges of impersonating an FBI agent in an alleged attempt to free Luigi Mangione from jail\nhttps://t.co/0VLqn3PlFb",
    "createdAt": "Thu Jan 29 20:54:22 +0000 2026",
    "metrics": {
      "likes": 0,
      "retweets": 0,
      "replies": 0,
      "views": "135963"
    }
  },
  {
    "user": {
      "screenName": "MebFaber",
      "name": "Meb Faber",
      "followersCount": 137308
    },
    "images": [
      "https://pbs.twimg.com/media/G_27i7CbUAE-aDE.png"
    ],
    "videos": [],
    "tweetUrl": "https://x.com/MebFaber/status/2016974429629403216",
    "fullText": "👻 https://t.co/j97B9bz31e",
    "createdAt": "Thu Jan 29 20:39:12 +0000 2026",
    "metrics": {
      "likes": 0,
      "retweets": 0,
      "replies": 0,
      "views": "31462"
    }
  },
  {
    "user": {
      "screenName": "DellAnnaLuca",
      "name": "Luca Dellanna",
      "followersCount": 25444
    },
    "images": [
      "https://pbs.twimg.com/media/G_2xT7OX0AAmet9.jpg"
    ],
    "videos": [],
    "tweetUrl": "https://x.com/DellAnnaLuca/status/2016963172356276484",
    "fullText": "Amazon shipped the 30 books I ordered (all identical, bought in the same session) in 30 individual packages https://t.co/ShTjyKhN0a",
    "createdAt": "Thu Jan 29 19:54:28 +0000 2026",
    "metrics": {
      "likes": 0,
      "retweets": 0,
      "replies": 0,
      "views": "3032"
    }
  },
  {
    "user": {
      "screenName": "nntaleb",
      "name": "Nassim Nicholas Taleb",
      "followersCount": 1123075
    },
    "images": [
      "https://pbs.twimg.com/media/G_2jJrrXkAEhyZg.jpg"
    ],
    "videos": [],
    "tweetUrl": "https://x.com/nntaleb/status/2016947610272354399",
    "fullText": "SILVER RULE &amp; AGEISM\nThere is a high probability that sociopaths like @normonics time-blind enough to not realize that they too will age, will end up 1) poor, 2) sickly, 3) bitter, 4)abandoned, 4) w/children turned woke/communists, 5) &amp; insulted by younger time-blind sociopaths https://t.co/aOCa69wqwq",
    "createdAt": "Thu Jan 29 18:52:38 +0000 2026",
    "metrics": {
      "likes": 0,
      "retweets": 0,
      "replies": 0,
      "views": "39426"
    }
  },
  {
    "user": {
      "screenName": "PolitiFact",
      "name": "PolitiFact",
      "followersCount": 584950
    },
    "images": [],
    "videos": [],
    "tweetUrl": "https://x.com/PolitiFact/status/2016942924022305250",
    "fullText": "¿Cuáles derechos tienes si te detiene ICE en la calle? ¿O si agentes de inmigración llegan a tu casa? ¿Puedes demandar si violan tus derechos? Expertos legales dan su opinión. https://t.co/1KNgL1gSnV",
    "createdAt": "Thu Jan 29 18:34:00 +0000 2026",
    "metrics": {
      "likes": 0,
      "retweets": 0,
      "replies": 0,
      "views": "3566"
    }
  },
  {
    "user": {
      "screenName": "WSJmarkets",
      "name": "WSJ Markets",
      "followersCount": 1021083
    },
    "images": [],
    "videos": [],
    "tweetUrl": "https://x.com/WSJmarkets/status/2016935436640239808",
    "fullText": "A $140 million loss at BlackRock is reviving questions about the accuracy of financial disclosures to individual investors in the booming private-credit industry https://t.co/RnnijQvKdD",
    "createdAt": "Thu Jan 29 18:04:15 +0000 2026",
    "metrics": {
      "likes": 0,
      "retweets": 0,
      "replies": 0,
      "views": "5878"
    }
  },
  {
    "user": {
      "screenName": "WSJmarkets",
      "name": "WSJ Markets",
      "followersCount": 1021083
    },
    "images": [],
    "videos": [],
    "tweetUrl": "https://x.com/WSJmarkets/status/2016933105257349534",
    "fullText": "President Trump’s regulators said they were ready to lay out rules that would help foster the crypto industry’s growth after legislation on the matter ran into an unexpected setback https://t.co/5wMWUeobhM",
    "createdAt": "Thu Jan 29 17:54:59 +0000 2026",
    "metrics": {
      "likes": 0,
      "retweets": 0,
      "replies": 0,
      "views": "3151"
    }
  },
  {
    "user": {
      "screenName": "cnnbrk",
      "name": "CNN Breaking News",
      "followersCount": 59265651
    },
    "images": [
      "https://pbs.twimg.com/media/G_2SleUWwAIvMIC.jpg"
    ],
    "videos": [],
    "tweetUrl": "https://x.com/cnnbrk/status/2016929401649156440",
    "fullText": "The Senate has blocked a massive funding bill as critical talks continue to avoid a government shutdown this weekend https://t.co/xkFRoGpU9d https://t.co/axkja1S7Q6",
    "createdAt": "Thu Jan 29 17:40:16 +0000 2026",
    "metrics": {
      "likes": 0,
      "retweets": 0,
      "replies": 0,
      "views": "122134"
    }
  },
  {
    "user": {
      "screenName": "cnnbrk",
      "name": "CNN Breaking News",
      "followersCount": 59265651
    },
    "images": [
      "https://pbs.twimg.com/media/G_2I0tNWUAAX6HT.jpg"
    ],
    "videos": [],
    "tweetUrl": "https://x.com/cnnbrk/status/2016918668093899162",
    "fullText": "Former Illinois deputy sentenced to 20 years in prison for killing Sonya Massey https://t.co/pPbzzwuwu2 https://t.co/oN1bbUeRlM",
    "createdAt": "Thu Jan 29 16:57:37 +0000 2026",
    "metrics": {
      "likes": 0,
      "retweets": 0,
      "replies": 0,
      "views": "96726"
    }
  },
  {
    "user": {
      "screenName": "nntaleb",
      "name": "Nassim Nicholas Taleb",
      "followersCount": 1123075
    },
    "images": [],
    "videos": [],
    "tweetUrl": "https://x.com/nntaleb/status/2016912359558938795",
    "fullText": "MACRO\nIn a long financial career, I've focused on derivatives (convexity) &amp; reverse tail risk.  Only handful of large \"macro\" trades, w/rule ONLY when signal is very very high.\n\nGold/Silver (current position, held for a while, added over time)\n\nShort Long bonds during ZIRP",
    "createdAt": "Thu Jan 29 16:32:33 +0000 2026",
    "metrics": {
      "likes": 0,
      "retweets": 0,
      "replies": 0,
      "views": "196460"
    }
  },
  {
    "user": {
      "screenName": "mikeharrisNY",
      "name": "Michael Harris ∀p(p→◊Kp)",
      "followersCount": 32777
    },
    "images": [],
    "videos": [],
    "tweetUrl": "https://x.com/mikeharrisNY/status/2016902423474741259",
    "fullText": "Logging out to work on a PP presentation on a completely different subject. So different, that it makes no sense to even mention it.",
    "createdAt": "Thu Jan 29 15:53:04 +0000 2026",
    "metrics": {
      "likes": 0,
      "retweets": 0,
      "replies": 0,
      "views": "856"
    }
  },
  {
    "user": {
      "screenName": "mikeharrisNY",
      "name": "Michael Harris ∀p(p→◊Kp)",
      "followersCount": 32777
    },
    "images": [],
    "videos": [],
    "tweetUrl": "https://x.com/mikeharrisNY/status/2016901603639402773",
    "fullText": "$MSFT -12% $CRM -8.3%",
    "createdAt": "Thu Jan 29 15:49:49 +0000 2026",
    "metrics": {
      "likes": 0,
      "retweets": 0,
      "replies": 0,
      "views": "765"
    }
  },
  {
    "user": {
      "screenName": "nntaleb",
      "name": "Nassim Nicholas Taleb",
      "followersCount": 1123075
    },
    "images": [],
    "videos": [],
    "tweetUrl": "https://x.com/nntaleb/status/2016900430639616101",
    "fullText": "NEW FILTER\nA sterile book or article is one that leaves no descendants and generates no further work.\n\nAlmost all books are sterile.",
    "createdAt": "Thu Jan 29 15:45:09 +0000 2026",
    "metrics": {
      "likes": 0,
      "retweets": 0,
      "replies": 0,
      "views": "45513"
    }
  },
  {
    "user": {
      "screenName": "PolitiFact",
      "name": "PolitiFact",
      "followersCount": 584950
    },
    "images": [],
    "videos": [],
    "tweetUrl": "https://x.com/PolitiFact/status/2016897631537029583",
    "fullText": "This isn’t a real photo of Minneapolis nurse Alex Pretti pinned down by federal immigration agents. The image has a digital watermark that shows it was generated using Google’s artificial intelligence tool, Gemini.\n\nhttps://t.co/vaY54WbM8Y",
    "createdAt": "Thu Jan 29 15:34:02 +0000 2026",
    "metrics": {
      "likes": 0,
      "retweets": 0,
      "replies": 0,
      "views": "3605"
    }
  },
  {
    "user": {
      "screenName": "mikeharrisNY",
      "name": "Michael Harris ∀p(p→◊Kp)",
      "followersCount": 32777
    },
    "images": [],
    "videos": [],
    "tweetUrl": "https://x.com/mikeharrisNY/status/2016893942428565806",
    "fullText": "The next Fed move should be a hike, but it will be a 0.5% cut under extreme pressure. But the hike will come eventually.",
    "createdAt": "Thu Jan 29 15:19:22 +0000 2026",
    "metrics": {
      "likes": 0,
      "retweets": 0,
      "replies": 0,
      "views": "657"
    }
  },
  {
    "user": {
      "screenName": "elerianm",
      "name": "Mohamed A. El-Erian",
      "followersCount": 803876
    },
    "images": [
      "https://pbs.twimg.com/media/G_1yHv5WMAAyaJj.jpg"
    ],
    "videos": [],
    "tweetUrl": "https://x.com/elerianm/status/2016893722642796668",
    "fullText": "From \"Hawks and Doves\" to \"Red and Blue\"?\nIn a sign of the times, this Wall Street Journal chart characterizes members of the Federal Reserve Board by their political nominations rather than their expertise, experience, or hawkish/dovish inclinations.\n#economy #FederalReserve https://t.co/MchCvVF2U9",
    "createdAt": "Thu Jan 29 15:18:30 +0000 2026",
    "metrics": {
      "likes": 0,
      "retweets": 0,
      "replies": 0,
      "views": "18814"
    }
  },
  {
    "user": {
      "screenName": "DellAnnaLuca",
      "name": "Luca Dellanna",
      "followersCount": 25444
    },
    "images": [],
    "videos": [],
    "tweetUrl": "https://x.com/DellAnnaLuca/status/2016892852576583983",
    "fullText": "Why do apps show new features to users upon loading, when the user has something urgent to do?\n\nThey should instead show them right after the user completes or submits an in-app task: that's when the user is calm and ready to listen.",
    "createdAt": "Thu Jan 29 15:15:02 +0000 2026",
    "metrics": {
      "likes": 0,
      "retweets": 0,
      "replies": 0,
      "views": "394"
    }
  },
  {
    "user": {
      "screenName": "mikeharrisNY",
      "name": "Michael Harris ∀p(p→◊Kp)",
      "followersCount": 32777
    },
    "images": [],
    "videos": [],
    "tweetUrl": "https://x.com/mikeharrisNY/status/2016892650230608239",
    "fullText": "Coppa +8%. Not enough coppa for the AI video demand.",
    "createdAt": "Thu Jan 29 15:14:14 +0000 2026",
    "metrics": {
      "likes": 0,
      "retweets": 0,
      "replies": 0,
      "views": "610"
    }
  },
  {
    "user": {
      "screenName": "mikeharrisNY",
      "name": "Michael Harris ∀p(p→◊Kp)",
      "followersCount": 32777
    },
    "images": [],
    "videos": [],
    "tweetUrl": "https://x.com/mikeharrisNY/status/2016891687969210876",
    "fullText": "It's Friday tomorrow, so all assets must go down today and ruin your weekend. This is how it works. $SPY $TLT $GLD $UUP",
    "createdAt": "Thu Jan 29 15:10:25 +0000 2026",
    "metrics": {
      "likes": 0,
      "retweets": 0,
      "replies": 0,
      "views": "1081"
    }
  },
  {
    "user": {
      "screenName": "PolitiFact",
      "name": "PolitiFact",
      "followersCount": 584950
    },
    "images": [],
    "videos": [],
    "tweetUrl": "https://x.com/PolitiFact/status/2016882526636122179",
    "fullText": "Dozens of U.S. metro areas have a higher concentration of immigrants in the U.S. illegally than the Minneapolis area. Vice President JD Vance’s statement that it has the highest concentration is wrong.\n\nhttps://t.co/ikVZvF9lhZ",
    "createdAt": "Thu Jan 29 14:34:00 +0000 2026",
    "metrics": {
      "likes": 0,
      "retweets": 0,
      "replies": 0,
      "views": "3860"
    }
  },
  {
    "user": {
      "screenName": "cnnbrk",
      "name": "CNN Breaking News",
      "followersCount": 59265651
    },
    "images": [
      "https://pbs.twimg.com/media/G_1n0yiWEAAwX-j.jpg"
    ],
    "videos": [],
    "tweetUrl": "https://x.com/cnnbrk/status/2016882385686581727",
    "fullText": "Trump's border czar says he ordered work on a plan to eventually reduce the number of agents in Minnesota and that misconduct would be \"dealt with\". https://t.co/zuufbZMMHl https://t.co/97gQgDEDIO",
    "createdAt": "Thu Jan 29 14:33:27 +0000 2026",
    "metrics": {
      "likes": 0,
      "retweets": 0,
      "replies": 0,
      "views": "92889"
    }
  },
  {
    "user": {
      "screenName": "WSJmarkets",
      "name": "WSJ Markets",
      "profileImageUrl": "https://pbs.twimg.com/profile_images/954404826212904960/TnG97-_8_normal.jpg",
      "description": "Breaking news, smart analysis and in-depth features on global markets and finance from The Wall Street Journal.",
      "followersCount": 1021079,
      "friendsCount": 520,
      "location": "New York, NY"
    },
    "images": [],
    "videos": [],
    "tweetUrl": "https://x.com/WSJmarkets/status/2016880737757130988",
    "fullText": "U.S. Natural Gas Gains As Front Month Shifts to March https://t.co/FviGvS46Qy"
  },
  {
    "user": {
      "screenName": "SecScottBessent",
      "name": "Treasury Secretary Scott Bessent",
      "profileImageUrl": "https://pbs.twimg.com/profile_images/1889401757060444160/MDUd0e0g_normal.jpg",
      "description": "79th United States Secretary of the Treasury",
      "followersCount": 806029,
      "friendsCount": 25,
      "location": ""
    },
    "images": [
      "https://pbs.twimg.com/media/G_1lx90bUAMUByx.jpg"
    ],
    "videos": [],
    "tweetUrl": "https://x.com/SecScottBessent/status/2016880123044073851",
    "fullText": "Trump Accounts mark a singular moment in American history, in which @POTUS democratized the benefits of private ownership and compound growth for all Americans.\n\nThank you, @NICKIMINAJ, for helping us to share this opportunity with the next generation. https://t.co/g6XckJF1Hj"
  },
  {
    "user": {
      "screenName": "NobelPrize",
      "name": "The Nobel Prize",
      "profileImageUrl": "https://pbs.twimg.com/profile_images/1029729528548139009/fVPd0EwX_normal.jpg",
      "description": "The official feed of the Nobel Prize @NobelPrize #NobelPrize",
      "followersCount": 1309884,
      "friendsCount": 496,
      "location": "Stockholm, Sweden"
    },
    "images": [
      "https://pbs.twimg.com/media/G_1j2rNXYAAB0SK.jpg"
    ],
    "videos": [],
    "tweetUrl": "https://x.com/NobelPrize/status/2016878020024242484",
    "fullText": "\"Looking back over my life, I am struck by the good fortune I have had to be a scientist. Very few in this world have the opportunity to do everyday what they love to do, as I have.\"\n\n- medicine laureate Linda Buck, who discovered how our sense of smell works.\n\n#NobelPrize https://t.co/vTtVaYsEww"
  },
  {
    "user": {
      "screenName": "TalebWisdom",
      "name": "Nassim Nicholas Taleb's Wisdom",
      "profileImageUrl": "https://pbs.twimg.com/profile_images/1111476570986893313/6r7zCbGa_normal.png",
      "description": "Sharing Nassim Nicholas Taleb's Wisdom from his books, interviews, and tweets. \n\n👇 GET YOUR FREE COPY of all awesome things about Nassim Nicholas Taleb",
      "followersCount": 136966,
      "friendsCount": 6,
      "location": ""
    },
    "images": [
      "https://pbs.twimg.com/media/G95vj9dXYAIqJTn.jpg"
    ],
    "videos": [],
    "tweetUrl": "https://x.com/TalebWisdom/status/2016869437736178166",
    "fullText": "https://t.co/9Xfk8xPvDX"
  },
  {
    "user": {
      "screenName": "PolitiFact",
      "name": "PolitiFact",
      "profileImageUrl": "https://pbs.twimg.com/profile_images/1286766140115517441/8rq6ZxZm_normal.jpg",
      "description": "Home of the Truth-O-Meter and independent fact-checking. Part of @Poynter. Sign up for our newsletter: https://t.co/9ygUqAw2P8",
      "followersCount": 584953,
      "friendsCount": 7182,
      "location": "Washington, DC"
    },
    "images": [],
    "videos": [],
    "tweetUrl": "https://x.com/PolitiFact/status/2016867428450332837",
    "fullText": "Rep. Jared Moskowitz, D-Fla. is largely right that FEMA’s current backlog of pending disaster applications is substantial, experts said. An analysis found applications have been pending longer than at any other time during the last 37 years\n\nhttps://t.co/qkTCkmCpDc"
  },
  {
    "user": {
      "screenName": "RobinRoberts",
      "name": "Robin Roberts",
      "profileImageUrl": "https://pbs.twimg.com/profile_images/1928115994653786112/lKrs82Io_normal.jpg",
      "description": "Good Morning America Anchor",
      "followersCount": 949018,
      "friendsCount": 1676,
      "location": "New York"
    },
    "images": [],
    "videos": [],
    "tweetUrl": "https://x.com/RobinRoberts/status/2016865914516541702",
    "fullText": "The Hot Chocolate competition is heating up this morn! Next on @GMA it’s the finale of our “U.S. of Hot Chocolate” search…and the owners of the four shops are here LIVE in studio. So who will win the 10-thousand-dollar prize?🤔"
  },
  {
    "user": {
      "screenName": "PaulPortesi",
      "name": "Paul Portesi",
      "profileImageUrl": "https://pbs.twimg.com/profile_images/1531335215896858624/42LKL7Dh_normal.jpg",
      "description": "Comments are from a nonsensical pontificator which are unscientific, unreasonable, illogical, unacademic nonevidentiary perspective https://t.co/wAsroKIpae",
      "followersCount": 10685,
      "friendsCount": 0,
      "location": ""
    },
    "images": [],
    "videos": [],
    "tweetUrl": "https://x.com/PaulPortesi/status/2016864159271702904",
    "fullText": "You may teach it, but that doesn't mean they have to learn."
  }
]